prometheus_remote_writer/__init__.py
prometheus_remote_writer/proto/gogoproto/__init__.py
prometheus_remote_writer/proto/gogoproto/gogo_pb2.py
prometheus_remote_writer/proto/remote_pb2.py
prometheus_remote_writer/proto/types_pb2.py
prometheus_remote_writer-1.1.3.dist-info/LICENSE
prometheus_remote_writer-1.1.3.dist-info/METADATA
prometheus_remote_writer-1.1.3.dist-info/WHEEL
prometheus_remote_writer-1.1.3.dist-info/RECORD
