Metadata-Version: 2.3
Name: prometheus-remote-writer
Version: 1.1.3
Summary: A Python package to send data using Prometheus remote write protocol.
License: Apache-2.0
Author: xy.kong
Author-email: xy.kong@gmail.com
Requires-Python: >=3.9,<4
Classifier: License :: OSI Approved :: Apache Software License
Classifier: Programming Language :: Python :: 3
Classifier: Programming Language :: Python :: 3.9
Classifier: Programming Language :: Python :: 3.10
Classifier: Programming Language :: Python :: 3.11
Classifier: Programming Language :: Python :: 3.12
Classifier: Programming Language :: Python :: 3.13
Requires-Dist: grpcio-tools (>=1.74.0,<2.0.0)
Requires-Dist: python-snappy (>=0.7.3,<0.8.0)
Requires-Dist: requests (>=2.32.5,<3.0.0)
